boaz_words/__init__.py
boaz_words/counter.py
boaz_words-0.0.2.dist-info/METADATA
boaz_words-0.0.2.dist-info/WHEEL
boaz_words-0.0.2.dist-info/top_level.txt
boaz_words-0.0.2.dist-info/RECORD
